copy_content/__init__.py
copy_content/__main__.py
copy_content-1.0.4.dist-info/LICENSE
copy_content-1.0.4.dist-info/METADATA
copy_content-1.0.4.dist-info/WHEEL
copy_content-1.0.4.dist-info/top_level.txt
copy_content-1.0.4.dist-info/RECORD
